<?xml version="1.0" encoding="UTF-8"?>

<tourist-vouchers xmlns:xsi="http://www.w3.org/2001/XMLSchema-instance"
                  xmlns="http://www.training.by/tourist-vouchers"
                  xsi:schemaLocation="http://www.training.by/tourist-vouchers tourist-vouchers.xsd">


    <city-break id="qwerty11" country="Россия" number-nights="1">
        <begin-data>2019-03-20T15:30:00</begin-data>
        <transport>Railway</transport>
        <cost currency="USD">
            <price>100</price>
            <flight-include>true</flight-include>
            <hotel-include>true</hotel-include>
        </cost>
        <hotel-characteristic number-stars="3" meal-type="AL" room-type="3">
            <tv>true</tv>
            <fan>true</fan>
            <safe>false</safe>
            <wi-fi>true</wi-fi>
        </hotel-characteristic>
        <shopping-centers-numbers>10</shopping-centers-numbers>
    </city-break>

    <guided-tour id="qwerty12" country="Турция" number-nights="10">
        <begin-data>2019-03-15T08:00:00</begin-data>
        <transport>Air</transport>
        <cost currency="BYN">
            <price>1500</price>
            <flight-include>true</flight-include>
            <hotel-include>true</hotel-include>
        </cost>
        <hotel-characteristic number-stars="4" room-type="2" meal-type="AL">
            <tv>true</tv>
            <fan>true</fan>
            <safe>false</safe>
            <wi-fi>true</wi-fi>
        </hotel-characteristic>
        <tour-guide>true</tour-guide>
        <excursions-number>8</excursions-number>
    </guided-tour>


    <rest id="qwerty13" country="Poland" number-nights="5">
        <begin-data>2019-03-30T12:16:00</begin-data>
        <transport>Railway</transport>
        <cost currency="BYN">
            <price>400</price>
            <flight-include>false</flight-include>
            <hotel-include>false</hotel-include>
        </cost>
        <hotel-characteristic number-stars="3" room-type="1" meal-type="HB">
            <tv>false</tv>
            <fan>true</fan>
            <safe>false</safe>
            <wi-fi>true</wi-fi>
        </hotel-characteristic>
        <resting>true</resting>
    </rest>
    <pilgrimage-tour id="qwerty14" country="India">
        <begin-data>2018-12-25T14:25:00</begin-data>
        <transport>Air</transport>
        <cost>
            <price>1000</price>
            <hotel-include>true</hotel-include>
            <flight-include>true</flight-include>
        </cost>
        <hotel-characteristic number-stars="3" room-type="1" meal-type="HB">
            <tv>false</tv>
            <safe>true</safe>
            <fan>true</fan>
            <wi-fi>false</wi-fi>
        </hotel-characteristic>
        <bethel-number>6</bethel-number>
    </pilgrimage-tour>

    <city-break id="qwerty15" country="Польша" number-nights="2">
        <begin-data>2019-01-20T14:30:00</begin-data>
        <transport>Air</transport>
        <cost currency="USD">
            <price>200</price>
            <flight-include>true</flight-include>
            <hotel-include>true</hotel-include>
        </cost>
        <hotel-characteristic number-stars="3" meal-type="AL" room-type="3">
            <tv>true</tv>
            <fan>true</fan>
            <safe>false</safe>
            <wi-fi>false</wi-fi>
        </hotel-characteristic>
        <shopping-centers-numbers>15</shopping-centers-numbers>
    </city-break>

    <guided-tour id="qwerty16" country="Египет" number-nights="12">
        <begin-data>2019-02-01T09:00:00</begin-data>
        <transport>Air</transport>
        <cost currency="USD">
            <price>1600</price>
            <flight-include>true</flight-include>
            <hotel-include>true</hotel-include>
        </cost>
        <hotel-characteristic number-stars="4" room-type="1" meal-type="AL">
            <tv>false</tv>
            <fan>true</fan>
            <safe>false</safe>
            <wi-fi>true</wi-fi>
        </hotel-characteristic>
        <tour-guide>true</tour-guide>
        <excursions-number>9</excursions-number>
    </guided-tour>


    <rest id="qwerty17" country="Франция" number-nights="2">
        <begin-data>2019-02-18T12:30:00</begin-data>
        <transport>Bus</transport>
        <cost>
            <price>600</price>
            <flight-include>true</flight-include>
            <hotel-include>false</hotel-include>
        </cost>
        <hotel-characteristic number-stars="3" room-type="2" meal-type="HB">
            <tv>false</tv>
            <fan>true</fan>
            <safe>false</safe>
            <wi-fi>false</wi-fi>
        </hotel-characteristic>
        <resting>true</resting>
    </rest>
    <pilgrimage-tour id="qwerty18" country="Китай" number-nights="6">
        <begin-data>2018-10-10T12:15:00</begin-data>
        <transport>Air</transport>
        <cost>
            <price>800</price>
            <hotel-include>true</hotel-include>
            <flight-include>true</flight-include>
        </cost>
        <hotel-characteristic number-stars="4" room-type="1" meal-type="HB">
            <tv>false</tv>
            <safe>true</safe>
            <fan>true</fan>
            <wi-fi>false</wi-fi>
        </hotel-characteristic>
        <bethel-number>8</bethel-number>
    </pilgrimage-tour>

    <city-break id="qwerty19" country="Франция" number-nights="3">
        <begin-data>2018-02-10T15:30:00</begin-data>
        <transport>Car</transport>
        <cost>
            <price>1000</price>
            <flight-include>true</flight-include>
            <hotel-include>true</hotel-include>
        </cost>
        <hotel-characteristic number-stars="3" meal-type="AL" room-type="2">
            <tv>true</tv>
            <fan>true</fan>
            <safe>true</safe>
            <wi-fi>false</wi-fi>
        </hotel-characteristic>
        <shopping-centers-numbers>6</shopping-centers-numbers>
    </city-break>

    <guided-tour id="qwerty20" country="Италия" number-nights="5">
        <begin-data>2019-04-16T08:00:00</begin-data>
        <transport>Railway</transport>
        <cost>
            <price>1000</price>
            <flight-include>true</flight-include>
            <hotel-include>true</hotel-include>
        </cost>
        <hotel-characteristic number-stars="4" room-type="2" meal-type="AL">
            <tv>true</tv>
            <fan>false</fan>
            <safe>false</safe>
            <wi-fi>true</wi-fi>
        </hotel-characteristic>
        <tour-guide>false</tour-guide>
        <excursions-number>5</excursions-number>
    </guided-tour>

    <rest id="qwerty21" country="Финляндия" number-nights="6">
        <begin-data>2019-05-16T12:16:00</begin-data>
        <transport>Liner</transport>
        <cost>
            <price>1000</price>
            <flight-include>false</flight-include>
            <hotel-include>true</hotel-include>
        </cost>
        <hotel-characteristic number-stars="3" room-type="2" meal-type="AL">
            <tv>true</tv>
            <fan>true</fan>
            <safe>true</safe>
            <wi-fi>true</wi-fi>
        </hotel-characteristic>
        <resting>true</resting>
    </rest>
    <pilgrimage-tour id="qwerty21" country="Индия" number-nights="6">
        <begin-data>2019-04-23T14:25:00</begin-data>
        <transport>Railway</transport>
        <cost>
            <price>1000</price>
            <hotel-include>true</hotel-include>
            <flight-include>true</flight-include>
        </cost>
        <hotel-characteristic number-stars="3" room-type="1" meal-type="HB">
            <tv>false</tv>
            <safe>true</safe>
            <fan>true</fan>
            <wi-fi>false</wi-fi>
        </hotel-characteristic>
        <bethel-number>6</bethel-number>
    </pilgrimage-tour>

    <city-break id="qwerty22" country="Чехия">
        <begin-data>2019-06-23T15:30:00</begin-data>
        <transport>Car</transport>
        <cost currency="USD">
            <price>600</price>
            <flight-include>true</flight-include>
            <hotel-include>true</hotel-include>
        </cost>
        <hotel-characteristic number-stars="3" meal-type="AL" room-type="3">
            <tv>true</tv>
            <fan>true</fan>
            <safe>false</safe>
            <wi-fi>true</wi-fi>
        </hotel-characteristic>
        <shopping-centers-numbers>5</shopping-centers-numbers>
    </city-break>

    <guided-tour id="qwerty23" country="Украина" number-nights="5">
        <begin-data>2019-06-27T09:00:00</begin-data>
        <transport>Car</transport>
        <cost currency="BYN">
            <price>800</price>
            <flight-include>true</flight-include>
            <hotel-include>true</hotel-include>
        </cost>
        <hotel-characteristic number-stars="4" room-type="2" meal-type="AL">
            <tv>false</tv>
            <fan>true</fan>
            <safe>true</safe>
            <wi-fi>true</wi-fi>
        </hotel-characteristic>
        <tour-guide>true</tour-guide>
        <excursions-number>6</excursions-number>
    </guided-tour>


    <rest id="qwerty24" country="Швеция" number-nights="5">
        <begin-data>2019-09-12T12:16:00</begin-data>
        <transport>Liner</transport>
        <cost>
            <price>1500</price>
            <flight-include>false</flight-include>
            <hotel-include>false</hotel-include>
        </cost>
        <hotel-characteristic number-stars="3" room-type="2" meal-type="AL">
            <tv>true</tv>
            <fan>true</fan>
            <safe>false</safe>
            <wi-fi>true</wi-fi>
        </hotel-characteristic>
        <resting>true</resting>
    </rest>

    <pilgrimage-tour id="qwerty25" country="Япония" number-nights="5">
        <begin-data>2019-02-20T14:25:00</begin-data>
        <transport>Air</transport>
        <cost>
            <price>1000</price>
            <hotel-include>true</hotel-include>
            <flight-include>true</flight-include>
        </cost>
        <hotel-characteristic number-stars="3" room-type="1" meal-type="HB">
            <tv>false</tv>
            <safe>true</safe>
            <fan>true</fan>
            <wi-fi>false</wi-fi>
        </hotel-characteristic>
        <bethel-number>7</bethel-number>
    </pilgrimage-tour>

    <guided-tour id="qwerty26" country="Испания" number-nights="7">
        <begin-data>2019-07-01T03:15:00</begin-data>
        <transport>Bus</transport>
        <cost>
            <price>1000</price>
            <flight-include>true</flight-include>
            <hotel-include>false</hotel-include>
        </cost>
        <hotel-characteristic number-stars="4" room-type="2" meal-type="HB">
            <tv>false</tv>
            <fan>true</fan>
            <safe>true</safe>
            <wi-fi>true</wi-fi>
        </hotel-characteristic>
        <tour-guide>false</tour-guide>
        <excursions-number>4</excursions-number>
    </guided-tour>
    <rest id="qwerty27" country="Великобритания" number-nights="6">
        <begin-data>2019-05-29T14:16:00</begin-data>
        <transport>Air</transport>
        <cost currency="USD">
            <price>2000</price>
            <flight-include>true</flight-include>
            <hotel-include>true</hotel-include>
        </cost>
        <hotel-characteristic number-stars="5" room-type="2" meal-type="AL">
            <tv>true</tv>
            <fan>true</fan>
            <safe>true</safe>
            <wi-fi>true</wi-fi>
        </hotel-characteristic>
        <resting>true</resting>
    </rest>

    <city-break id="qwerty28" country="Норвегия">
        <begin-data>2019-05-16T15:00:00</begin-data>
        <transport>Bus</transport>
        <cost>
            <price>600</price>
            <flight-include>true</flight-include>
            <hotel-include>true</hotel-include>
        </cost>
        <hotel-characteristic number-stars="3" room-type="1" meal-type="AL">
            <tv>true</tv>
            <fan>true</fan>
            <safe>true</safe>
            <wi-fi>true</wi-fi>
        </hotel-characteristic>
        <shopping-centers-numbers>4</shopping-centers-numbers>
    </city-break>
</tourist-vouchers>

